another_sender/__init__.py
another_sender/cli.py
another_sender/history_utils.py
another_sender/menu_utils.py
another_sender/meta_utils.py
another_sender/spi_utils.py
another_sender/udp_utils.py
another_sender-0.1.5.dist-info/licenses/LICENSE
another_sender-0.1.5.dist-info/METADATA
another_sender-0.1.5.dist-info/WHEEL
another_sender-0.1.5.dist-info/entry_points.txt
another_sender-0.1.5.dist-info/top_level.txt
another_sender-0.1.5.dist-info/RECORD
