Metadata-Version: 2.4
Name: another-sender
Version: 0.1.5
Summary: CLI to send command files over UDP, SPI, and more.
Home-page: https://github.com/minipcb/another-sender
Author: Nolan Manteufel
License: MIT
Project-URL: Homepage, https://github.com/miniPCB/another-sender
Classifier: Programming Language :: Python :: 3
Classifier: Operating System :: OS Independent
Requires-Python: >=3.7
License-File: LICENSE
Dynamic: home-page
Dynamic: license-file
Dynamic: requires-python
